{
	"credit": "Made with Blockbench",
	"textures": {
		"0": "Desktop/hhhh",
		"particle": "Desktop/hhhh"
	},
	"elements": [
		{
			"from": [4, -4, 4],
			"to": [12, 4, 12],
			"rotation": {"angle": 0, "axis": "y", "origin": [12, 4, 12]},
			"faces": {
				"north": {"uv": [0, 0, 8, 8], "texture": "#0"},
				"east": {"uv": [0, 0, 8, 8], "texture": "#0"},
				"south": {"uv": [0, 0, 8, 8], "texture": "#0"},
				"west": {"uv": [0, 0, 8, 8], "texture": "#0"},
				"up": {"uv": [0, 0, 8, 8], "texture": "#0"},
				"down": {"uv": [0, 0, 8, 8], "texture": "#0"}
			}
		}
	]
}